maap_dps_jupyter_extension/__init__.py
maap_dps_jupyter_extension/_version.py
maap_dps_jupyter_extension-0.7.7.data/data/share/jupyter/labextensions/maap_dps_jupyter_extension/package.json
maap_dps_jupyter_extension-0.7.7.data/data/share/jupyter/labextensions/maap_dps_jupyter_extension/static/100.b351f4dc28bacf7c6681.js
maap_dps_jupyter_extension-0.7.7.data/data/share/jupyter/labextensions/maap_dps_jupyter_extension/static/101.9463bb462fc138d9e853.js
maap_dps_jupyter_extension-0.7.7.data/data/share/jupyter/labextensions/maap_dps_jupyter_extension/static/101.9463bb462fc138d9e853.js.LICENSE.txt
maap_dps_jupyter_extension-0.7.7.data/data/share/jupyter/labextensions/maap_dps_jupyter_extension/static/199.854195054532a4cff972.js
maap_dps_jupyter_extension-0.7.7.data/data/share/jupyter/labextensions/maap_dps_jupyter_extension/static/376.c1dc4ca07da3642ef9f3.js
maap_dps_jupyter_extension-0.7.7.data/data/share/jupyter/labextensions/maap_dps_jupyter_extension/static/376.c1dc4ca07da3642ef9f3.js.LICENSE.txt
maap_dps_jupyter_extension-0.7.7.data/data/share/jupyter/labextensions/maap_dps_jupyter_extension/static/421.b541e0d5c702546f0b83.js
maap_dps_jupyter_extension-0.7.7.data/data/share/jupyter/labextensions/maap_dps_jupyter_extension/static/566.75c4ecadb819a7f3be75.js
maap_dps_jupyter_extension-0.7.7.data/data/share/jupyter/labextensions/maap_dps_jupyter_extension/static/719.b351f4dc28bacf7c6681.js
maap_dps_jupyter_extension-0.7.7.data/data/share/jupyter/labextensions/maap_dps_jupyter_extension/static/723.56df3da20a780024b0fb.js
maap_dps_jupyter_extension-0.7.7.data/data/share/jupyter/labextensions/maap_dps_jupyter_extension/static/728.27cbbf17cd6ec86692fa.js
maap_dps_jupyter_extension-0.7.7.data/data/share/jupyter/labextensions/maap_dps_jupyter_extension/static/782.6b94b464f4da8b262e30.js
maap_dps_jupyter_extension-0.7.7.data/data/share/jupyter/labextensions/maap_dps_jupyter_extension/static/782.6b94b464f4da8b262e30.js.LICENSE.txt
maap_dps_jupyter_extension-0.7.7.dist-info/METADATA
maap_dps_jupyter_extension-0.7.7.dist-info/WHEEL
maap_dps_jupyter_extension-0.7.7.dist-info/licenses/LICENSE
maap_dps_jupyter_extension-0.7.7.dist-info/RECORD
